app_min.py
nano_numwords-0.1.2.dist-info/licenses/LICENSE
nano_numwords-0.1.2.dist-info/METADATA
nano_numwords-0.1.2.dist-info/WHEEL
nano_numwords-0.1.2.dist-info/entry_points.txt
nano_numwords-0.1.2.dist-info/top_level.txt
nano_numwords-0.1.2.dist-info/RECORD
