Metadata-Version: 2.4
Name: nano-numwords
Version: 0.1.2
Summary: Tiny English word→number parser in ~1KB
Author: ozgunlu
License: MIT
Requires-Python: >=3.8
License-File: LICENSE
Dynamic: license-file
